<?xml version="1.0" encoding="us-ascii"?>
<Catalog>
  <CModel default="1" id="UnitDeath">
    <?token id="Race" value="Neutral"?>
    <?token id="Prefix" value="Portraits\"?>
    <Flags index="Download" value="0" />
    <Flags index="FOW" value="0" />
    <Flags index="IgnoreAspectRatioScale" value="1" />
    <EditorCategories value="Race:##Race##" />
    <Image value="Assets\Textures\##id##_Static.dds" />
    <Model value="Assets\##Prefix####Race##\##id##\##id##.m3" />
    <Quality value="0" />
    <AnimBlendTime value="0.500000" />
    <Priority value="8" />
    <PausedParticleSystemBehavior value="FreezeAll" />
  </CModel>
  <CModel default="1" id="StasisWardDeathBase" parent="UnitDeath">
    <?token id="Race" value="Protoss"?>
    <?token id="low" type="CModelLink" value="ProtossSmallUnitDeathLow"?>
  </CModel>
</Catalog>
